kiowaplatform/__init__.py
kiowaplatform/audit.py
kiowaplatform/datawrangling.py
kiowaplatform/platform.py
kiowaplatform/resource.py
kiowaplatform/resource_fridge.py
kiowaplatform/test_datawrangling.py
kiowaplatform/test_platform.py
kiowaplatform-0.0.11.dist-info/METADATA
kiowaplatform-0.0.11.dist-info/WHEEL
kiowaplatform-0.0.11.dist-info/top_level.txt
kiowaplatform-0.0.11.dist-info/RECORD
